<Localizer language="Español - BSAS" associatedCulture="es-AR">
  <String>
    <Original>...</Original>
    <Translated>...</Translated>
  </String>
  <String>
    <Original>About Territories Management</Original>
    <Translated>Acerca de Territories Management</Translated>
  </String>
  <String>
    <Original>Additional information</Original>
    <Translated>Información adicional</Translated>
  </String>
  <String>
    <Original>Address</Original>
    <Translated>Dirección</Translated>
  </String>
  <String>
    <Original>Address data</Original>
    <Translated>Datos de la dirección</Translated>
  </String>
  <String>
    <Original>Addresses</Original>
    <Translated>Direcciones</Translated>
  </String>
  <String>
    <Original>Apply</Original>
    <Translated>Aplicar</Translated>
  </String>
  <String>
    <Original>Area</Original>
    <Translated>Area</Translated>
  </String>
  <String>
    <Original>Autoselect</Original>
    <Translated>Autoseleccionar</Translated>
  </String>
  <String>
    <Original>Begin</Original>
    <Translated>Inicio</Translated>
  </String>
  <String>
    <Original>Between</Original>
    <Translated>Entre</Translated>
  </String>
  <String>
    <Original>Cancel</Original>
    <Translated>Cancelar</Translated>
  </String>
  <String>
    <Original>Cities</Original>
    <Translated>Ciudades</Translated>
  </String>
  <String>
    <Original>City</Original>
    <Translated>Ciudad</Translated>
  </String>
  <String>
    <Original>Clear area</Original>
    <Translated>Limpiar area</Translated>
  </String>
  <String>
    <Original>Configuration</Original>
    <Translated>Configuración</Translated>
  </String>
  <String>
    <Original>Configure</Original>
    <Translated>Configurar</Translated>
  </String>
  <String>
    <Original>Configure import properties</Original>
    <Translated>Configurar propiedades de importación</Translated>
  </String>
  <String>
    <Original>Connection status:</Original>
    <Translated>Estado de la conección:</Translated>
  </String>
  <String>
    <Original>Connection string</Original>
    <Translated>Cadena de conección</Translated>
  </String>
  <String>
    <Original>Copy (Google Maps)</Original>
    <Translated>Copiar (Google Maps)</Translated>
  </String>
  <String>
    <Original>Corner 1</Original>
    <Translated>Esquina 1</Translated>
  </String>
  <String>
    <Original>Corner 2</Original>
    <Translated>Esquina 2</Translated>
  </String>
  <String>
    <Original>Corners</Original>
    <Translated>Esquinas</Translated>
  </String>
  <String>
    <Original>Cultures</Original>
    <Translated>Culturas</Translated>
  </String>
  <String>
    <Original>Custom field 1</Original>
    <Translated>Campo personalizado 1</Translated>
  </String>
  <String>
    <Original>Data</Original>
    <Translated>Datos</Translated>
  </String>
  <String>
    <Original>Data export</Original>
    <Translated>Exportación de datos</Translated>
  </String>
  <String>
    <Original>Data import</Original>
    <Translated>Importación de datos</Translated>
  </String>
  <String>
    <Original>Delete</Original>
    <Translated>Borrar</Translated>
  </String>
  <String>
    <Original>Department</Original>
    <Translated>Partido</Translated>
  </String>
  <String>
    <Original>Departments</Original>
    <Translated>Partidos</Translated>
  </String>
  <String>
    <Original>Description</Original>
    <Translated>Descripción</Translated>
  </String>
  <String>
    <Original>Edit</Original>
    <Translated>Editar</Translated>
  </String>
  <String>
    <Original>End</Original>
    <Translated>Fin</Translated>
  </String>
  <String>
    <Original>Error</Original>
    <Translated>Error</Translated>
  </String>
  <String>
    <Original>Error. </Original>
    <Translated>Error. </Translated>
  </String>
  <String>
    <Original>Export</Original>
    <Translated>Exportar</Translated>
  </String>
  <String>
    <Original>Export data</Original>
    <Translated>Exportar datos</Translated>
  </String>
  <String>
    <Original>Export records</Original>
    <Translated>Exportar registros</Translated>
  </String>
  <String>
    <Original>Export to excel file</Original>
    <Translated>Exportar a Excel</Translated>
  </String>
  <String>
    <Original>Export to Gmaps</Original>
    <Translated>Exportar a GMaps</Translated>
  </String>
  <String>
    <Original>External data</Original>
    <Translated>Datos externos</Translated>
  </String>
  <String>
    <Original>Filter by city name</Original>
    <Translated>Filtrar por ciudad</Translated>
  </String>
  <String>
    <Original>Filter by department</Original>
    <Translated>Filtrar por partido</Translated>
  </String>
  <String>
    <Original>Filter by department name</Original>
    <Translated>Filtrar por ciudad</Translated>
  </String>
  <String>
    <Original>Filter by territory name</Original>
    <Translated>Filtrar por territorio</Translated>
  </String>
  <String>
    <Original>Filtered</Original>
    <Translated>Filtrado</Translated>
  </String>
  <String>
    <Original>GEO</Original>
    <Translated>GEO</Translated>
  </String>
  <String>
    <Original>Geo data has been imported.</Original>
    <Translated>Los datos geográficos fueron importados.</Translated>
  </String>
  <String>
    <Original>Geo location</Original>
    <Translated>Geo localización.</Translated>
  </String>
  <String>
    <Original>Go</Original>
    <Translated>Ir</Translated>
  </String>
  <String>
    <Original>Has geoposition</Original>
    <Translated>Tiene geoposición</Translated>
  </String>
  <String>
    <Original>Help</Original>
    <Translated>Ayuda</Translated>
  </String>
  <String>
    <Original>Hide relations</Original>
    <Translated>Ocultar relaciones</Translated>
  </String>
  <String>
    <Original>Id</Original>
    <Translated>Id</Translated>
  </String>
  <String>
    <Original>Import</Original>
    <Translated>Importar</Translated>
  </String>
  <String>
    <Original>Import from GeoRss file</Original>
    <Translated>Importar desde GeoRSS</Translated>
  </String>
  <String>
    <Original>Import records</Original>
    <Translated>Importar registros</Translated>
  </String>
  <String>
    <Original>Internal number</Original>
    <Translated>Número interno</Translated>
  </String>
  <String>
    <Original>Interoperability</Original>
    <Translated>Interoperabilidad</Translated>
  </String>
  <String>
    <Original>Lat</Original>
    <Translated>Lat</Translated>
  </String>
  <String>
    <Original>Latitude</Original>
    <Translated>Latitud</Translated>
  </String>
  <String>
    <Original>Lng</Original>
    <Translated>Lng</Translated>
  </String>
  <String>
    <Original>Location</Original>
    <Translated>Ubicación</Translated>
  </String>
  <String>
    <Original>Longitude</Original>
    <Translated>Longitud</Translated>
  </String>
  <String>
    <Original>Map 1</Original>
    <Translated>Mapa 1</Translated>
  </String>
  <String>
    <Original>Map 2</Original>
    <Translated>Mapa 2</Translated>
  </String>
  <String>
    <Original>Map type</Original>
    <Translated>Tipo de mapa</Translated>
  </String>
  <String>
    <Original>Maps</Original>
    <Translated>Mapas</Translated>
  </String>
  <String>
    <Original>Menu</Original>
    <Translated>Menu</Translated>
  </String>
  <String>
    <Original>Name</Original>
    <Translated>Nombre</Translated>
  </String>
  <String>
    <Original>New</Original>
    <Translated>Nuevo</Translated>
  </String>
  <String>
    <Original>Number</Original>
    <Translated>Número</Translated>
  </String>
  <String>
    <Original>Ok</Original>
    <Translated>Ok</Translated>
  </String>
  <String>
    <Original>OK. Last modification date: </Original>
    <Translated>OK. Fecha de última mod:</Translated>
  </String>
  <String>
    <Original>Phone 1</Original>
    <Translated>Teléfono 1</Translated>
  </String>
  <String>
    <Original>Phone 2</Original>
    <Translated>Teléfono 2</Translated>
  </String>
  <String>
    <Original>Phone numbers</Original>
    <Translated>Teléfonos</Translated>
  </String>
  <String>
    <Original>Place</Original>
    <Translated>Lugar</Translated>
  </String>
  <String>
    <Original>Publisher</Original>
    <Translated>Publicador</Translated>
  </String>
  <String>
    <Original>Publishers</Original>
    <Translated>Publicadores</Translated>
  </String>
  <String>
    <Original>Region, Country</Original>
    <Translated>Provincia, País</Translated>
  </String>
  <String>
    <Original>Reset</Original>
    <Translated>Restablecer</Translated>
  </String>
  <String>
    <Original>Result</Original>
    <Translated>Resultado</Translated>
  </String>
  <String>
    <Original>Result:</Original>
    <Translated>Resultado:</Translated>
  </String>
  <String>
    <Original>Save</Original>
    <Translated>Guardar</Translated>
  </String>
  <String>
    <Original>Search</Original>
    <Translated>Buscar</Translated>
  </String>
  <String>
    <Original>Select</Original>
    <Translated>Seleccionar</Translated>
  </String>
  <String>
    <Original>Select culture</Original>
    <Translated>Seleccionar cultura</Translated>
  </String>
  <String>
    <Original>Select map type</Original>
    <Translated>Seleccionar tipo de mapa</Translated>
  </String>
  <String>
    <Original>Select source and destination files.</Original>
    <Translated>Selecionar origen y destino.</Translated>
  </String>
  <String>
    <Original>Street</Original>
    <Translated>Calle</Translated>
  </String>
  <String>
    <Original>Street and Nº</Original>
    <Translated>Calle y altura</Translated>
  </String>
  <String>
    <Original>Territories</Original>
    <Translated>Territorios</Translated>
  </String>
  <String>
    <Original>Territories Management</Original>
    <Translated>Territories Management</Translated>
  </String>
  <String>
    <Original>Territory</Original>
    <Translated>Territorio</Translated>
  </String>
  <String>
    <Original>The data is incomplete.</Original>
    <Translated>Los datos son incompletos.</Translated>
  </String>
  <String>
    <Original>The exportation has been successful.\n</Original>
    <Translated>La exportación se ha realizado exitosamente.\n</Translated>
  </String>
  <String>
    <Original>The exportation has problems. Check the settings and see the log.\n</Original>
    <Translated>La exportación tuvo algunos problemas. Revise las configuraciones y el registro.\n</Translated>
  </String>
  <String>
    <Original>The importation has been successful.</Original>
    <Translated>La importación se ha realizado exitosamente.</Translated>
  </String>
  <String>
    <Original>The importation has problems. Check the settings and see the log.</Original>
    <Translated>La importación tuvo algunos problemas. Revise las configuraciones y el registro.\n</Translated>
  </String>
  <String>
    <Original>The window is already open.</Original>
    <Translated>La ventana ya está abierta.</Translated>
  </String>
  <String>
    <Original>There is some unsaved data. Do you want to continue?</Original>
    <Translated>Hay datos sin guardar. Desea continuar?</Translated>
  </String>
  <String>
    <Original>To Excel</Original>
    <Translated>A Excel</Translated>
  </String>
  <String>
    <Original>To GMap</Original>
    <Translated>A GMaps</Translated>
  </String>
  <String>
    <Original>To image</Original>
    <Translated>Imagen</Translated>
  </String>
  <String>
    <Original>Tools</Original>
    <Translated>Herramientas</Translated>
  </String>
  <String>
    <Original>Tour Nº</Original>
    <Translated>Recorrido Nº</Translated>
  </String>
  <String>
    <Original>Tours</Original>
    <Translated>Recorridos</Translated>
  </String>
  <String>
    <Original>Update</Original>
    <Translated>Guardar</Translated>
  </String>
  <String>
    <Original>View</Original>
    <Translated>Ver</Translated>
  </String>
  <String>
    <Original>View map</Original>
    <Translated>Ver mapa</Translated>
  </String>
  <String>
    <Original>View relations</Original>
    <Translated>Ver relaciones</Translated>
  </String>
  <String>
    <Original>You must complete at least one search criteria.</Original>
    <Translated>Debe completar al menos un criterio de búsqueda.</Translated>
  </String>
  <String>
    <Original>You must select a city</Original>
    <Translated>Debe seleccionar una ciudad.</Translated>
  </String>
  <String>
    <Original>You must select a department</Original>
    <Translated>Debe seleccionar un partido.</Translated>
  </String>
  <String>
    <Original>You must select at least one search criteria.</Original>
    <Translated>You must select at least one search criteria.</Translated>
  </String>
  <String>
    <Original>You must select at least one search field.</Original>
    <Translated>You must select at least one search field.</Translated>
  </String>
  <String>
    <Original>You must select an address.</Original>
    <Translated>Debe seleccionar una dirección.</Translated>
  </String>
  <String>
    <Original>You must select a territory.</Original>
    <Translated>Debe seleccionar un territorio.</Translated>
  </String>
</Localizer>